RYMTracks-0.1.4.dist-info/top_level.txt
RYMTracks-0.1.4.dist-info/WHEEL
RYMTracks-0.1.4.dist-info/pydist.json
RYMTracks-0.1.4.dist-info/entry_points.txt
RYMTracks-0.1.4.dist-info/METADATA
RYMTracks-0.1.4.dist-info/RECORD
RYMTracks-0.1.4.dist-info/DESCRIPTION.rst
RYMTracks-0.1.4.data/scripts/rymtracks
rymtracks/formatters.py
rymtracks/utils.py
rymtracks/core.py
rymtracks/__init__.py
rymtracks/services/__init__.py
rymtracks/services/base/mixins.py
rymtracks/services/base/water.py
rymtracks/services/base/__init__.py
rymtracks/services/base/service.py
rymtracks/services/base/webservice.py
rymtracks/services/implementations/rateyourmusic.py
rymtracks/services/implementations/allmusic.py
rymtracks/services/implementations/freemusicarchive.py
rymtracks/services/implementations/amazon.py
rymtracks/services/implementations/boomkat.py
rymtracks/services/implementations/sevendigital.py
rymtracks/services/implementations/progarchives.py
rymtracks/services/implementations/__init__.py
rymtracks/services/implementations/discogs.py
rymtracks/services/implementations/musicbrainz.py
rymtracks/services/implementations/archiveorg.py
rymtracks/services/implementations/bandcamp.py
rymtracks/services/implementations/itunes.py
rymtracks/services/implementations/beatport.py
rymtracks/services/implementations/junodownload.py
rymtracks/services/implementations/jamendo.py
rymtracks/services/implementations/lastfm.py
rymtracks/services/implementations/filesystem.py
rymtracks/capitalization/py3.py
rymtracks/capitalization/__init__.py
rymtracks/capitalization/py2.py
